MANIFEST.in
README.rst
dev-requirements.txt
requirements.txt
setup.cfg
setup.py
test-requirements.txt
clusto_apiserver.egg-info/PKG-INFO
clusto_apiserver.egg-info/SOURCES.txt
clusto_apiserver.egg-info/dependency_links.txt
clusto_apiserver.egg-info/entry_points.txt
clusto_apiserver.egg-info/not-zip-safe
clusto_apiserver.egg-info/pbr.json
clusto_apiserver.egg-info/top_level.txt
clustoapi/__init__.py
clustoapi/server.py
clustoapi/util.py
clustoapi/apps/__init__.py
clustoapi/apps/attribute.py
clustoapi/apps/entity.py
clustoapi/apps/resourcemanager.py
tests/__init__.py
tests/all.py
tests/suites/__init__.py
tests/suites/coding_style.py
tests/suites/python_docs.py
tests/suites/shell_docs.py
tests/suites/util.py