Metadata-Version: 1.1
Name: clusto-apiserver
Version: 0.5.2
Summary: RESTful API server to interact with the clusto database.
Home-page: https://github.com/clusto/clusto-apiserver
Author: Jorge Gallegos
Author-email: kad@blegh.net
License: BSD
Platform: UNKNOWN
Classifier: Development Status :: 4 - Beta
Classifier: Environment :: Web Environment
Classifier: Framework :: Bottle
Classifier: Intended Audience :: System Administrators
Classifier: License :: OSI Approved :: BSD License
Classifier: Operating System :: OS Independent
Classifier: Programming Language :: Python
Classifier: Topic :: Internet :: WWW/HTTP :: WSGI :: Application
